pyEfsMounter
