Metadata-Version: 1.0
Name: py-efs-mounter
Version: 0.1.1
Summary: Mount and unmount to efs
Home-page: https://github.com/njfix6/py-efs-mounter
Author: Nicholas Fix
Author-email: njfix6@gmail.com
License: UNKNOWN
Platform: UNKNOWN
